channels_redis/__init__.py
channels_redis/core.py
channels_redis/pubsub.py
channels_redis/serializers.py
channels_redis/utils.py
channels_redis2-4.2.1.dist-info/LICENSE
channels_redis2-4.2.1.dist-info/METADATA
channels_redis2-4.2.1.dist-info/WHEEL
channels_redis2-4.2.1.dist-info/top_level.txt
channels_redis2-4.2.1.dist-info/RECORD
