Metadata-Version: 2.1
Name: channels_redis2
Version: 4.2.1
Summary: Redis-backed ASGI channel layer implementation
Home-page: http://github.com/django/channels_redis/
Author: Django Software Foundation
Author-email: foundation@djangoproject.com
Requires-Python: >=3.8
License-File: LICENSE
Requires-Dist: redis>=4.6
Requires-Dist: msgpack~=1.0
Requires-Dist: asgiref<4,>=3.2.10
Requires-Dist: channels
Provides-Extra: cryptography
Requires-Dist: cryptography>=1.3.0; extra == "cryptography"
Provides-Extra: tests
Requires-Dist: cryptography>=1.3.0; extra == "tests"
Requires-Dist: pytest; extra == "tests"
Requires-Dist: pytest-asyncio; extra == "tests"
Requires-Dist: async-timeout; extra == "tests"
Requires-Dist: pytest-timeout; extra == "tests"
